[
  {
    "bbox": [
      [
        32.0,
        33.0
      ],
      [
        398.0,
        33.0
      ],
      [
        398.0,
        65.0
      ],
      [
        32.0,
        65.0
      ]
    ],
    "text": "Welche international ausgerichteten Stu-",
    "confidence": 0.9614272890201477
  },
  {
    "bbox": [
      [
        421.0,
        33.0
      ],
      [
        802.0,
        33.0
      ],
      [
        802.0,
        66.0
      ],
      [
        421.0,
        66.0
      ]
    ],
    "text": "Zunehmend bieten Schulen die Möglichkeit,",
    "confidence": 0.9369491413259334
  },
  {
    "bbox": [
      [
        31.0,
        57.0
      ],
      [
        399.0,
        57.0
      ],
      [
        399.0,
        94.0
      ],
      [
        31.0,
        94.0
      ]
    ],
    "text": "diengänge werden angeboten; in die Aus-",
    "confidence": 0.915541359235581
  },
  {
    "bbox": [
      [
        422.0,
        60.0
      ],
      [
        804.0,
        60.0
      ],
      [
        804.0,
        88.0
      ],
      [
        422.0,
        88.0
      ]
    ],
    "text": "die für eine direkte Aufnahme eines Studi -",
    "confidence": 0.7428997070706722
  },
  {
    "bbox": [
      [
        31.0,
        87.0
      ],
      [
        398.0,
        87.0
      ],
      [
        398.0,
        118.0
      ],
      [
        31.0,
        118.0
      ]
    ],
    "text": "landssemester von vornherein integriert",
    "confidence": 0.8934222629734562
  },
  {
    "bbox": [
      [
        422.0,
        88.0
      ],
      [
        804.0,
        88.0
      ],
      [
        804.0,
        119.0
      ],
      [
        422.0,
        119.0
      ]
    ],
    "text": "ums im Ausland vorausgesetzte Sprachprü-",
    "confidence": 0.695637238876602
  },
  {
    "bbox": [
      [
        32.0,
        112.0
      ],
      [
        399.0,
        112.0
      ],
      [
        399.0,
        145.0
      ],
      [
        32.0,
        145.0
      ]
    ],
    "text": "sind? Besteht die Möglichkeit einer Dop-",
    "confidence": 0.7738631706451209
  },
  {
    "bbox": [
      [
        420.0,
        113.0
      ],
      [
        804.0,
        113.0
      ],
      [
        804.0,
        144.0
      ],
      [
        420.0,
        144.0
      ]
    ],
    "text": "fung bereits während der Schulzeit abzule-",
    "confidence": 0.8288865790443143
  },
  {
    "bbox": [
      [
        30.0,
        137.0
      ],
      [
        399.0,
        137.0
      ],
      [
        399.0,
        173.0
      ],
      [
        30.0,
        173.0
      ]
    ],
    "text": "pelqualifikation (vgl. Abschnitte 4.1.4 und",
    "confidence": 0.6018341534140369
  },
  {
    "bbox": [
      [
        422.0,
        140.0
      ],
      [
        804.0,
        140.0
      ],
      [
        804.0,
        170.0
      ],
      [
        422.0,
        170.0
      ]
    ],
    "text": "gen. So zB. das Advanced Placement Inter-",
    "confidence": 0.6505725813238179
  },
  {
    "bbox": [
      [
        420.0,
        163.0
      ],
      [
        805.0,
        163.0
      ],
      [
        805.0,
        199.0
      ],
      [
        420.0,
        199.0
      ]
    ],
    "text": "national English Language Examination",
    "confidence": 0.586039537004331
  },
  {
    "bbox": [
      [
        32.0,
        168.0
      ],
      [
        94.0,
        168.0
      ],
      [
        94.0,
        194.0
      ],
      [
        32.0,
        194.0
      ]
    ],
    "text": "4.1.51?",
    "confidence": 0.5514280288468784
  },
  {
    "bbox": [
      [
        422.0,
        190.0
      ],
      [
        804.0,
        190.0
      ],
      [
        804.0,
        222.0
      ],
      [
        422.0,
        222.0
      ]
    ],
    "text": "(APIEL). Dieses standardisierte internationa-",
    "confidence": 0.7657933297750011
  },
  {
    "bbox": [
      [
        34.0,
        195.0
      ],
      [
        398.0,
        195.0
      ],
      [
        398.0,
        225.0
      ],
      [
        34.0,
        225.0
      ]
    ],
    "text": "Welche Versicherungsfragen sind zu klären?",
    "confidence": 0.6549403927037057
  },
  {
    "bbox": [
      [
        422.0,
        218.0
      ],
      [
        804.0,
        218.0
      ],
      [
        804.0,
        248.0
      ],
      [
        422.0,
        248.0
      ]
    ],
    "text": "le Sprachexamen kann bereits in der Ober-",
    "confidence": 0.6994219265053806
  },
  {
    "bbox": [
      [
        343.07899166023174,
        225.14487414671834
      ],
      [
        399.8706417299283,
        234.12855518912892
      ],
      [
        394.92100833976826,
        261.85512585328166
      ],
      [
        338.1293582700717,
        252.87144481087108
      ]
    ],
    "text": "Ange-",
    "confidence": 0.9996648207307878
  },
  {
    "bbox": [
      [
        18.0,
        228.0
      ],
      [
        342.0,
        228.0
      ],
      [
        342.0,
        260.0
      ],
      [
        18.0,
        260.0
      ]
    ],
    "text": "Erkundigen Sie sich ggf. auch, welche",
    "confidence": 0.6623935193471687
  },
  {
    "bbox": [
      [
        421.0,
        242.0
      ],
      [
        805.0,
        242.0
      ],
      [
        805.0,
        280.0
      ],
      [
        421.0,
        280.0
      ]
    ],
    "text": "stufe abgelegt werden und wird mittlerweile",
    "confidence": 0.8214183494383744
  },
  {
    "bbox": [
      [
        16.0,
        254.0
      ],
      [
        398.0,
        254.0
      ],
      [
        398.0,
        282.0
      ],
      [
        16.0,
        282.0
      ]
    ],
    "text": "bote und Hilfen für Studierende mit Behinde-",
    "confidence": 0.9472920738176547
  },
  {
    "bbox": [
      [
        421.0,
        267.0
      ],
      [
        805.0,
        267.0
      ],
      [
        805.0,
        305.0
      ],
      [
        421.0,
        305.0
      ]
    ],
    "text": "in fast allen Bundesländern angeboten",
    "confidence": 0.8034109289335525
  },
  {
    "bbox": [
      [
        16.0,
        280.0
      ],
      [
        398.0,
        280.0
      ],
      [
        398.0,
        310.0
      ],
      [
        16.0,
        310.0
      ]
    ],
    "text": "rungen oder chronischen Krankheiten ange-",
    "confidence": 0.959885924728629
  },
  {
    "bbox": [
      [
        422.0,
        298.0
      ],
      [
        636.0,
        298.0
      ],
      [
        636.0,
        328.0
      ],
      [
        422.0,
        328.0
      ]
    ],
    "text": "(www.collegeboard org).",
    "confidence": 0.3881250401057693
  },
  {
    "bbox": [
      [
        16.0,
        308.0
      ],
      [
        398.0,
        308.0
      ],
      [
        398.0,
        334.0
      ],
      [
        16.0,
        334.0
      ]
    ],
    "text": "boten werden . Erste Informationen können",
    "confidence": 0.6771143880519467
  },
  {
    "bbox": [
      [
        422.0,
        328.0
      ],
      [
        804.0,
        328.0
      ],
      [
        804.0,
        361.0
      ],
      [
        422.0,
        361.0
      ]
    ],
    "text": "Das D.ALF (Diplome Approfondi en Langue",
    "confidence": 0.5772619609238604
  },
  {
    "bbox": [
      [
        16.0,
        334.0
      ],
      [
        398.0,
        334.0
      ],
      [
        398.0,
        364.0
      ],
      [
        16.0,
        364.0
      ]
    ],
    "text": "Sie bei der vInformations-und Beratungsstel -",
    "confidence": 0.6843409792037222
  },
  {
    "bbox": [
      [
        421.0,
        355.0
      ],
      [
        804.0,
        355.0
      ],
      [
        804.0,
        387.0
      ],
      [
        421.0,
        387.0
      ]
    ],
    "text": "Francaise) ist auf das Universitätsstudium aus-",
    "confidence": 0.9685839462827199
  },
  {
    "bbox": [
      [
        16.0,
        357.0
      ],
      [
        398.0,
        357.0
      ],
      [
        398.0,
        390.0
      ],
      [
        16.0,
        390.0
      ]
    ],
    "text": "le Studium und Behinderungw des Deutschen",
    "confidence": 0.5490929082039212
  },
  {
    "bbox": [
      [
        420.0,
        378.0
      ],
      [
        806.0,
        378.0
      ],
      [
        806.0,
        414.0
      ],
      [
        420.0,
        414.0
      ]
    ],
    "text": "gerichtet . Es bescheinigt; dass die sprachli-",
    "confidence": 0.7535120261261979
  },
  {
    "bbox": [
      [
        15.0,
        385.0
      ],
      [
        240.0,
        385.0
      ],
      [
        240.0,
        415.0
      ],
      [
        15.0,
        415.0
      ]
    ],
    "text": "Studentenwerks erhalten:",
    "confidence": 0.8321845601067472
  },
  {
    "bbox": [
      [
        422.0,
        408.0
      ],
      [
        804.0,
        408.0
      ],
      [
        804.0,
        441.0
      ],
      [
        422.0,
        441.0
      ]
    ],
    "text": "chen Voraussetzungen vorhandenen sind, um",
    "confidence": 0.7035327042589037
  },
  {
    "bbox": [
      [
        18.0,
        416.0
      ],
      [
        398.0,
        416.0
      ],
      [
        398.0,
        449.0
      ],
      [
        18.0,
        449.0
      ]
    ],
    "text": "Um Ihr Studium im Ausland optimal vorzube-",
    "confidence": 0.6682780099631386
  },
  {
    "bbox": [
      [
        424.0,
        436.0
      ],
      [
        804.0,
        436.0
      ],
      [
        804.0,
        462.0
      ],
      [
        424.0,
        462.0
      ]
    ],
    "text": "an einer französischen Universität in einem",
    "confidence": 0.7607804764053443
  },
  {
    "bbox": [
      [
        16.0,
        442.0
      ],
      [
        398.0,
        442.0
      ],
      [
        398.0,
        472.0
      ],
      [
        16.0,
        472.0
      ]
    ],
    "text": "reiten, lohnt es sich mithin; bereits bei der",
    "confidence": 0.5386817821012935
  },
  {
    "bbox": [
      [
        422.0,
        462.0
      ],
      [
        804.0,
        462.0
      ],
      [
        804.0,
        490.0
      ],
      [
        422.0,
        490.0
      ]
    ],
    "text": "Fach seiner Wahl studieren zu können. Die In-",
    "confidence": 0.754636867540272
  },
  {
    "bbox": [
      [
        18.0,
        472.0
      ],
      [
        398.0,
        472.0
      ],
      [
        398.0,
        498.0
      ],
      [
        18.0,
        498.0
      ]
    ],
    "text": "Wahl der Heimathochschule darauf zu ach-",
    "confidence": 0.7243325315687131
  },
  {
    "bbox": [
      [
        421.0,
        485.0
      ],
      [
        805.0,
        485.0
      ],
      [
        805.0,
        522.0
      ],
      [
        421.0,
        522.0
      ]
    ],
    "text": "haber des D.ALF: sind deshalb von Eingangs-",
    "confidence": 0.7330942214178136
  },
  {
    "bbox": [
      [
        16.0,
        498.0
      ],
      [
        398.0,
        498.0
      ],
      [
        398.0,
        530.0
      ],
      [
        16.0,
        530.0
      ]
    ],
    "text": "ten; ob und welche Möglichkeiten für Aus-",
    "confidence": 0.6660273041781944
  },
  {
    "bbox": [
      [
        421.0,
        513.0
      ],
      [
        803.0,
        513.0
      ],
      [
        803.0,
        544.0
      ],
      [
        421.0,
        544.0
      ]
    ],
    "text": "sprachtests bei allen französischen Universitä -",
    "confidence": 0.8728560573042509
  },
  {
    "bbox": [
      [
        16.0,
        523.0
      ],
      [
        398.0,
        523.0
      ],
      [
        398.0,
        555.0
      ],
      [
        16.0,
        555.0
      ]
    ],
    "text": "landsaufenthalte dort angeboten werden; wie",
    "confidence": 0.7081976904199851
  },
  {
    "bbox": [
      [
        422.0,
        540.0
      ],
      [
        804.0,
        540.0
      ],
      [
        804.0,
        570.0
      ],
      [
        422.0,
        570.0
      ]
    ],
    "text": "ten befreit .  Spezielle Informationen für Schü-",
    "confidence": 0.7686829718509194
  },
  {
    "bbox": [
      [
        18.0,
        549.0
      ],
      [
        398.0,
        549.0
      ],
      [
        398.0,
        580.0
      ],
      [
        18.0,
        580.0
      ]
    ],
    "text": "man von der Hochschule organisatorisch und",
    "confidence": 0.8476135559439092
  },
  {
    "bbox": [
      [
        422.0,
        568.0
      ],
      [
        806.0,
        568.0
      ],
      [
        806.0,
        594.0
      ],
      [
        422.0,
        594.0
      ]
    ],
    "text": "lerinnen und Schüler sowie Studierende findet",
    "confidence": 0.585014874538374
  },
  {
    "bbox": [
      [
        16.0,
        577.0
      ],
      [
        398.0,
        577.0
      ],
      [
        398.0,
        606.0
      ],
      [
        16.0,
        606.0
      ]
    ],
    "text": "fachlich unterstützt werden kann. Neben den",
    "confidence": 0.8546624656150904
  },
  {
    "bbox": [
      [
        424.0,
        594.0
      ],
      [
        804.0,
        594.0
      ],
      [
        804.0,
        620.0
      ],
      [
        424.0,
        620.0
      ]
    ],
    "text": "man auf den Internetseiten der Instituts Fran-",
    "confidence": 0.7329515568012273
  },
  {
    "bbox": [
      [
        18.0,
        604.0
      ],
      [
        398.0,
        604.0
      ],
      [
        398.0,
        630.0
      ],
      [
        18.0,
        630.0
      ]
    ],
    "text": "Länderstudienführern des Deutschen Akade-",
    "confidence": 0.6467600946674485
  },
  {
    "bbox": [
      [
        422.0,
        620.0
      ],
      [
        804.0,
        620.0
      ],
      [
        804.0,
        650.0
      ],
      [
        422.0,
        650.0
      ]
    ],
    "text": "cais in Deutschland (wwwkultur-frankreich",
    "confidence": 0.6558669298285142
  },
  {
    "bbox": [
      [
        18.0,
        630.0
      ],
      [
        400.0,
        630.0
      ],
      [
        400.0,
        658.0
      ],
      [
        18.0,
        658.0
      ]
    ],
    "text": "mischen Austauschdienstes (DAADI, die für",
    "confidence": 0.84647328199415
  },
  {
    "bbox": [
      [
        428.0,
        646.0
      ],
      [
        804.0,
        646.0
      ],
      [
        804.0,
        674.0
      ],
      [
        428.0,
        674.0
      ]
    ],
    "text": "de) ebenso wie Links zu den verschiedenen",
    "confidence": 0.820370754289287
  },
  {
    "bbox": [
      [
        18.0,
        658.0
      ],
      [
        398.0,
        658.0
      ],
      [
        398.0,
        686.0
      ],
      [
        18.0,
        686.0
      ]
    ],
    "text": "eine Reihe von europäischen Ländern sowie",
    "confidence": 0.8683348515202363
  },
  {
    "bbox": [
      [
        423.0,
        669.0
      ],
      [
        805.0,
        669.0
      ],
      [
        805.0,
        706.0
      ],
      [
        423.0,
        706.0
      ]
    ],
    "text": "Sprachkursen und kostenlosen Einstufungs-",
    "confidence": 0.8832047137287192
  },
  {
    "bbox": [
      [
        15.0,
        679.0
      ],
      [
        400.0,
        679.0
      ],
      [
        400.0,
        718.0
      ],
      [
        15.0,
        718.0
      ]
    ],
    "text": "für einige außereuropäische Länder vorliegen;",
    "confidence": 0.8737593549821385
  },
  {
    "bbox": [
      [
        422.0,
        700.0
      ],
      [
        746.0,
        700.0
      ],
      [
        746.0,
        730.0
      ],
      [
        422.0,
        730.0
      ]
    ],
    "text": "tests an 24 Standorten in Deutschland.",
    "confidence": 0.8814272233546995
  },
  {
    "bbox": [
      [
        17.0,
        709.0
      ],
      [
        399.0,
        709.0
      ],
      [
        399.0,
        745.0
      ],
      [
        17.0,
        745.0
      ]
    ],
    "text": "gibt es zahlreiche Anlaufstellen und Informa-",
    "confidence": 0.9509179847321743
  },
  {
    "bbox": [
      [
        16.0,
        738.0
      ],
      [
        398.0,
        738.0
      ],
      [
        398.0,
        770.0
      ],
      [
        16.0,
        770.0
      ]
    ],
    "text": "tionsmöglichkeiten; die Sie frühzeitig in An-",
    "confidence": 0.7873292309031797
  },
  {
    "bbox": [
      [
        17.0,
        764.0
      ],
      [
        398.0,
        764.0
      ],
      [
        398.0,
        796.0
      ],
      [
        17.0,
        796.0
      ]
    ],
    "text": "spruch nehmen sollten (vgl. Abschnitt 4.1.7)!",
    "confidence": 0.8076318271455125
  },
  {
    "bbox": [
      [
        181.0,
        807.0
      ],
      [
        723.0,
        807.0
      ],
      [
        723.0,
        871.0
      ],
      [
        181.0,
        871.0
      ]
    ],
    "text": "Finanzierung und Förderprogramme",
    "confidence": 0.8660312309537648
  },
  {
    "bbox": [
      [
        105.0,
        819.0
      ],
      [
        183.0,
        819.0
      ],
      [
        183.0,
        857.0
      ],
      [
        105.0,
        857.0
      ]
    ],
    "text": "4.1.2",
    "confidence": 0.9606809261057035
  },
  {
    "bbox": [
      [
        424.0,
        871.0
      ],
      [
        804.0,
        871.0
      ],
      [
        804.0,
        904.0
      ],
      [
        424.0,
        904.0
      ]
    ],
    "text": "wenn Sie die Förderungsvoraussetzungen",
    "confidence": 0.9932617934044737
  },
  {
    "bbox": [
      [
        18.0,
        872.0
      ],
      [
        397.0,
        872.0
      ],
      [
        397.0,
        898.0
      ],
      [
        18.0,
        898.0
      ]
    ],
    "text": "Studieren im Ausland ist meistens kostenauf -",
    "confidence": 0.7280467883695082
  },
  {
    "bbox": [
      [
        18.0,
        898.0
      ],
      [
        400.0,
        898.0
      ],
      [
        400.0,
        928.0
      ],
      [
        18.0,
        928.0
      ]
    ],
    "text": "wendiger als das Studium an der Heimathoch -",
    "confidence": 0.6671034621952581
  },
  {
    "bbox": [
      [
        424.0,
        898.0
      ],
      [
        498.0,
        898.0
      ],
      [
        498.0,
        924.0
      ],
      [
        424.0,
        924.0
      ]
    ],
    "text": "erfüllen.",
    "confidence": 0.9362208024000208
  },
  {
    "bbox": [
      [
        18.0,
        924.0
      ],
      [
        400.0,
        924.0
      ],
      [
        400.0,
        955.0
      ],
      [
        18.0,
        955.0
      ]
    ],
    "text": "schule: Die Lebenshaltungskosten liegen in",
    "confidence": 0.6964720159301566
  },
  {
    "bbox": [
      [
        424.0,
        932.0
      ],
      [
        803.0,
        932.0
      ],
      [
        803.0,
        962.0
      ],
      [
        424.0,
        962.0
      ]
    ],
    "text": "Durch das Ausbildungsförderungsreformge-",
    "confidence": 0.8806198382245572
  },
  {
    "bbox": [
      [
        20.0,
        952.0
      ],
      [
        396.0,
        952.0
      ],
      [
        396.0,
        978.0
      ],
      [
        20.0,
        978.0
      ]
    ],
    "text": "manchen Ländern über denen in Deutschland.",
    "confidence": 0.7460481163330924
  },
  {
    "bbox": [
      [
        424.0,
        958.0
      ],
      [
        804.0,
        958.0
      ],
      [
        804.0,
        986.0
      ],
      [
        424.0,
        986.0
      ]
    ],
    "text": "setz können Sie seit dem 1. April 2001 inner-",
    "confidence": 0.8066540022959856
  },
  {
    "bbox": [
      [
        20.0,
        978.0
      ],
      [
        400.0,
        978.0
      ],
      [
        400.0,
        1010.0
      ],
      [
        20.0,
        1010.0
      ]
    ],
    "text": "Dies gilt jedoch zunehmend weniger für die",
    "confidence": 0.7313245423643474
  },
  {
    "bbox": [
      [
        424.0,
        984.0
      ],
      [
        806.0,
        984.0
      ],
      [
        806.0,
        1014.0
      ],
      [
        424.0,
        1014.0
      ]
    ],
    "text": "halb der EU nach einer einjährigen Startpha-",
    "confidence": 0.846731790867161
  },
  {
    "bbox": [
      [
        18.0,
        1003.0
      ],
      [
        400.0,
        1003.0
      ],
      [
        400.0,
        1034.0
      ],
      [
        18.0,
        1034.0
      ]
    ],
    "text": "EU-Staaten; wo die fortschreitende Verein -",
    "confidence": 0.6014675001091623
  },
  {
    "bbox": [
      [
        424.0,
        1008.0
      ],
      [
        806.0,
        1008.0
      ],
      [
        806.0,
        1038.0
      ],
      [
        424.0,
        1038.0
      ]
    ],
    "text": "se an einer deutschen Hochschule eine Aus-",
    "confidence": 0.9757656402958181
  },
  {
    "bbox": [
      [
        15.0,
        1027.0
      ],
      [
        401.0,
        1027.0
      ],
      [
        401.0,
        1065.0
      ],
      [
        15.0,
        1065.0
      ]
    ],
    "text": "heitlichung der Lebensverhältnisse; zu der",
    "confidence": 0.9061941042369464
  },
  {
    "bbox": [
      [
        424.0,
        1036.0
      ],
      [
        807.0,
        1036.0
      ],
      [
        807.0,
        1068.0
      ],
      [
        424.0,
        1068.0
      ]
    ],
    "text": "bildungsförderung bis zum Abschluss ihrer",
    "confidence": 0.9180037713718904
  },
  {
    "bbox": [
      [
        18.0,
        1055.0
      ],
      [
        398.0,
        1055.0
      ],
      [
        398.0,
        1088.0
      ],
      [
        18.0,
        1088.0
      ]
    ],
    "text": "auch die Einführung des Euro beiträgt, ten-",
    "confidence": 0.5517165686581886
  },
  {
    "bbox": [
      [
        425.0,
        1061.0
      ],
      [
        804.0,
        1061.0
      ],
      [
        804.0,
        1094.0
      ],
      [
        425.0,
        1094.0
      ]
    ],
    "text": "Ausbildung erhalten, wenn Sie die Ausbil-",
    "confidence": 0.6385317515477815
  },
  {
    "bbox": [
      [
        17.0,
        1080.0
      ],
      [
        401.0,
        1080.0
      ],
      [
        401.0,
        1121.0
      ],
      [
        17.0,
        1121.0
      ]
    ],
    "text": "denziell gleiche Bedingungen schafft. Neben",
    "confidence": 0.606371158698907
  },
  {
    "bbox": [
      [
        422.0,
        1090.0
      ],
      [
        806.0,
        1090.0
      ],
      [
        806.0,
        1122.0
      ],
      [
        422.0,
        1122.0
      ]
    ],
    "text": "dung innerhalb der Förderungshöchstdauer",
    "confidence": 0.6209745786123494
  },
  {
    "bbox": [
      [
        18.0,
        1109.0
      ],
      [
        400.0,
        1109.0
      ],
      [
        400.0,
        1142.0
      ],
      [
        18.0,
        1142.0
      ]
    ],
    "text": "der privaten Finanzierung durch Ersparnisse",
    "confidence": 0.8071545959223612
  },
  {
    "bbox": [
      [
        424.0,
        1114.0
      ],
      [
        806.0,
        1114.0
      ],
      [
        806.0,
        1144.0
      ],
      [
        424.0,
        1144.0
      ]
    ],
    "text": "absolvieren. In Österreich kann auch ein Voll-",
    "confidence": 0.7422156641682
  },
  {
    "bbox": [
      [
        18.0,
        1138.0
      ],
      [
        400.0,
        1138.0
      ],
      [
        400.0,
        1170.0
      ],
      [
        18.0,
        1170.0
      ]
    ],
    "text": "oder Unterstützung durch die Eltern gibt es",
    "confidence": 0.7654708464555426
  },
  {
    "bbox": [
      [
        423.0,
        1140.0
      ],
      [
        807.0,
        1140.0
      ],
      [
        807.0,
        1177.0
      ],
      [
        423.0,
        1177.0
      ]
    ],
    "text": "studium gefördert werden. Sie erhalten auch",
    "confidence": 0.8970589687531034
  },
  {
    "bbox": [
      [
        17.0,
        1162.0
      ],
      [
        375.0,
        1162.0
      ],
      [
        375.0,
        1198.0
      ],
      [
        17.0,
        1198.0
      ]
    ],
    "text": "eine Reihe von Förderungsmöglichkeiten:",
    "confidence": 0.9582394304257967
  },
  {
    "bbox": [
      [
        424.0,
        1170.0
      ],
      [
        806.0,
        1170.0
      ],
      [
        806.0,
        1198.0
      ],
      [
        424.0,
        1198.0
      ]
    ],
    "text": "im EU-Ausland den BAföG-Inlandssatz; die",
    "confidence": 0.7420783197296522
  },
  {
    "bbox": [
      [
        426.0,
        1198.0
      ],
      [
        806.0,
        1198.0
      ],
      [
        806.0,
        1228.0
      ],
      [
        426.0,
        1228.0
      ]
    ],
    "text": "bisher üblichen Auslandszuschläge fallen",
    "confidence": 0.7646498778942484
  },
  {
    "bbox": [
      [
        20.0,
        1210.0
      ],
      [
        92.0,
        1210.0
      ],
      [
        92.0,
        1240.0
      ],
      [
        20.0,
        1240.0
      ]
    ],
    "text": "BAföG",
    "confidence": 0.999785896242238
  },
  {
    "bbox": [
      [
        426.0,
        1224.0
      ],
      [
        808.0,
        1224.0
      ],
      [
        808.0,
        1254.0
      ],
      [
        426.0,
        1254.0
      ]
    ],
    "text": "weg. Der Studienort kann innerhalb der EU",
    "confidence": 0.655440253003294
  },
  {
    "bbox": [
      [
        20.0,
        1242.0
      ],
      [
        400.0,
        1242.0
      ],
      [
        400.0,
        1275.0
      ],
      [
        20.0,
        1275.0
      ]
    ],
    "text": "Auf die gesetzlichen Förderungsmaßnahmen",
    "confidence": 0.9299662395331997
  },
  {
    "bbox": [
      [
        425.0,
        1249.0
      ],
      [
        675.0,
        1249.0
      ],
      [
        675.0,
        1285.0
      ],
      [
        425.0,
        1285.0
      ]
    ],
    "text": "beliebig gewechselt werden:",
    "confidence": 0.8566076927676813
  },
  {
    "bbox": [
      [
        20.0,
        1272.0
      ],
      [
        400.0,
        1272.0
      ],
      [
        400.0,
        1302.0
      ],
      [
        20.0,
        1302.0
      ]
    ],
    "text": "nach dem Bundesausbildungsförderungsge-",
    "confidence": 0.9297146047658953
  },
  {
    "bbox": [
      [
        426.0,
        1283.0
      ],
      [
        806.0,
        1283.0
      ],
      [
        806.0,
        1312.0
      ],
      [
        426.0,
        1312.0
      ]
    ],
    "text": "Für das Studium in Nicht-EU-Staaten; also",
    "confidence": 0.6586590586176153
  },
  {
    "bbox": [
      [
        20.0,
        1298.0
      ],
      [
        400.0,
        1298.0
      ],
      [
        400.0,
        1328.0
      ],
      [
        20.0,
        1328.0
      ]
    ],
    "text": "setz (BAföG) haben Sie auch im Falle eines",
    "confidence": 0.7181578930835372
  },
  {
    "bbox": [
      [
        678.0,
        1310.0
      ],
      [
        808.0,
        1310.0
      ],
      [
        808.0,
        1342.0
      ],
      [
        678.0,
        1342.0
      ]
    ],
    "text": "die bisherigen",
    "confidence": 0.9929868332940516
  },
  {
    "bbox": [
      [
        426.0,
        1312.0
      ],
      [
        618.0,
        1312.0
      ],
      [
        618.0,
        1340.0
      ],
      [
        426.0,
        1340.0
      ]
    ],
    "text": "auch für die Schweiz,",
    "confidence": 0.7989895650532945
  },
  {
    "bbox": [
      [
        616.6027607015021,
        1313.3452453328541
      ],
      [
        676.6224718283646,
        1308.543071206464
      ],
      [
        678.3972392984979,
        1337.6547546671459
      ],
      [
        617.3775281716354,
        1341.456928793536
      ]
    ],
    "text": "gelten",
    "confidence": 0.9999673443307706
  },
  {
    "bbox": [
      [
        20.0,
        1326.0
      ],
      [
        398.0,
        1326.0
      ],
      [
        398.0,
        1354.0
      ],
      [
        20.0,
        1354.0
      ]
    ],
    "text": "Auslandsstudiums einen Rechtsanspruch,",
    "confidence": 0.9113062858219343
  },
  {
    "bbox": [
      [
        424.0,
        1336.0
      ],
      [
        807.0,
        1336.0
      ],
      [
        807.0,
        1372.0
      ],
      [
        424.0,
        1372.0
      ]
    ],
    "text": "Regelungen: Die Förderungsdauer im Ausland",
    "confidence": 0.8323658883108843
  }
]